warriorsnmp/__init__.py
warriorsnmp/Actions/__init__.py
warriorsnmp/Actions/SnmpActions/__init__.py
warriorsnmp/Actions/SnmpActions/common_snmp_actions.py
warriorsnmp/ClassUtils/__init__.py
warriorsnmp/ClassUtils/snmp_utlity_class.py
warriorsnmp/ProductDrivers/__init__.py
warriorsnmp/ProductDrivers/snmp_driver.py
warriorsnmp/Utils/__init__.py
warriorsnmp/Utils/snmp_utils.py
warriorsnmp-1.0.0.dist-info/METADATA
warriorsnmp-1.0.0.dist-info/WHEEL
warriorsnmp-1.0.0.dist-info/top_level.txt
warriorsnmp-1.0.0.dist-info/RECORD
